u_coreutils/__init__.py
u_coreutils/_base64/__init__.py
u_coreutils/_base64/__main__.py
u_coreutils/cat/__init__.py
u_coreutils/cat/__main__.py
u_coreutils/cat/pipeline.py
u_coreutils/echo/__init__.py
u_coreutils/echo/__main__.py
u_coreutils/factor/__init__.py
u_coreutils/factor/__main__.py
u_coreutils/false/__init__.py
u_coreutils/false/__main__.py
u_coreutils/head/__init__.py
u_coreutils/head/__main__.py
u_coreutils/mkdir/__init__.py
u_coreutils/mkdir/__main__.py
u_coreutils-0.1.11.dist-info/entry_points.txt
u_coreutils-0.1.11.dist-info/WHEEL
u_coreutils-0.1.11.dist-info/METADATA
u_coreutils-0.1.11.dist-info/RECORD
